{
	"id": "1940173f-7ce7-c8ba-2eb2-dd7ba2d22953",
	"name": "people10",
	"description": "",
	"order": [
		"72a1e74c-6430-eef7-1c4c-2b4aec965a37",
		"db87ee2d-a677-900d-ba8a-96408fa19294",
		"402b9c10-1814-6ba8-41df-4d01d77526b4",
		"a0d03b79-3965-bda1-91ac-8035360d52a1",
		"cbe726f0-f39f-985e-241e-aed3924b5447",
		"a5e2d666-5278-eda8-a068-cdaad762ee31"
	],
	"folders": [],
	"folders_order": [],
	"timestamp": 1594557667570,
	"owner": 0,
	"public": false,
	"requests": [
		{
			"id": "402b9c10-1814-6ba8-41df-4d01d77526b4",
			"headers": "",
			"headerData": [],
			"url": "http://localhost:8080/api/getCustomerId/{email}/{password}",
			"queryParams": [],
			"preRequestScript": null,
			"pathVariables": {},
			"pathVariableData": [],
			"method": "GET",
			"data": null,
			"dataMode": "params",
			"version": 2,
			"tests": null,
			"currentHelper": "normal",
			"helperAttributes": {},
			"time": 1594558485845,
			"name": "Get Customer Id",
			"description": "",
			"collectionId": "1940173f-7ce7-c8ba-2eb2-dd7ba2d22953",
			"responses": []
		},
		{
			"id": "72a1e74c-6430-eef7-1c4c-2b4aec965a37",
			"headers": "Content-Type: application/json\n",
			"headerData": [
				{
					"key": "Content-Type",
					"value": "application/json",
					"description": "",
					"enabled": true
				}
			],
			"url": "http://localhost:8080/api/addRoom",
			"queryParams": [],
			"preRequestScript": null,
			"pathVariables": {},
			"pathVariableData": [],
			"method": "POST",
			"data": [],
			"dataMode": "raw",
			"version": 2,
			"tests": null,
			"currentHelper": "normal",
			"helperAttributes": {},
			"time": 1594557709583,
			"name": "Add Room",
			"description": "",
			"collectionId": "1940173f-7ce7-c8ba-2eb2-dd7ba2d22953",
			"responses": [],
			"rawModeData": "{\"roomType\":\"K\",\"rent\":2500}"
		},
		{
			"id": "a0d03b79-3965-bda1-91ac-8035360d52a1",
			"headers": "",
			"headerData": [],
			"url": "http://localhost:8080/api/getCustomer/naveen.dpt2007@gmail.com/abc1234",
			"queryParams": [],
			"preRequestScript": null,
			"pathVariables": {},
			"pathVariableData": [],
			"method": "GET",
			"data": null,
			"dataMode": "params",
			"version": 2,
			"tests": null,
			"currentHelper": "normal",
			"helperAttributes": {},
			"time": 1594558583043,
			"name": "Get Customer",
			"description": "",
			"collectionId": "1940173f-7ce7-c8ba-2eb2-dd7ba2d22953",
			"responses": []
		},
		{
			"id": "a5e2d666-5278-eda8-a068-cdaad762ee31",
			"headers": "",
			"headerData": [],
			"url": "",
			"queryParams": [],
			"pathVariables": {},
			"pathVariableData": [],
			"preRequestScript": null,
			"method": "GET",
			"collectionId": "1940173f-7ce7-c8ba-2eb2-dd7ba2d22953",
			"data": null,
			"dataMode": "params",
			"name": "GetRoomsList",
			"description": "",
			"descriptionFormat": "html",
			"time": 1594563441651,
			"version": 2,
			"responses": [],
			"tests": null,
			"currentHelper": "normal",
			"helperAttributes": {}
		},
		{
			"id": "cbe726f0-f39f-985e-241e-aed3924b5447",
			"headers": "Content-Type: application/json\n",
			"headerData": [
				{
					"key": "Content-Type",
					"value": "application/json",
					"description": "",
					"enabled": true
				}
			],
			"url": "http://localhost:8080/api/bookRoom",
			"queryParams": [],
			"preRequestScript": null,
			"pathVariables": {},
			"pathVariableData": [],
			"method": "POST",
			"data": [],
			"dataMode": "raw",
			"version": 2,
			"tests": null,
			"currentHelper": "normal",
			"helperAttributes": {},
			"time": 1594562534850,
			"name": "Book Room",
			"description": "",
			"collectionId": "1940173f-7ce7-c8ba-2eb2-dd7ba2d22953",
			"responses": [],
			"rawModeData": "{\"roomId\":\"50003\",\"customerId\":\"70002\",\"startDate\":\"2020-01-04\",\"endDate\":\"2020-01-04\"}"
		},
		{
			"id": "db87ee2d-a677-900d-ba8a-96408fa19294",
			"headers": "Content-Type: application/json\n",
			"headerData": [
				{
					"key": "Content-Type",
					"value": "application/json",
					"description": "",
					"enabled": true
				}
			],
			"url": "http://localhost:8080/api/createCustomer",
			"queryParams": [],
			"preRequestScript": null,
			"pathVariables": {},
			"pathVariableData": [],
			"method": "POST",
			"data": [],
			"dataMode": "raw",
			"version": 2,
			"tests": null,
			"currentHelper": "normal",
			"helperAttributes": {},
			"time": 1594562453886,
			"name": "Create Customer",
			"description": "",
			"collectionId": "1940173f-7ce7-c8ba-2eb2-dd7ba2d22953",
			"responses": [],
			"rawModeData": "{\"firstName\":\"Naveen\",\"lastName\":\"Kumar\",\"dateOfBirth\":\"1988-11-20\",\"email\":\"naveen.dpt2020@gmail.com\",\"password\":\"abc123456\"}"
		}
	]
}